LICENSE
README.rst
setup.py
pftree/__init__.py
pftree/__main__.py
pftree/pftree.py
pftree.egg-info/PKG-INFO
pftree.egg-info/SOURCES.txt
pftree.egg-info/dependency_links.txt
pftree.egg-info/entry_points.txt
pftree.egg-info/not-zip-safe
pftree.egg-info/requires.txt
pftree.egg-info/top_level.txt