Metadata-Version: 2.1
Name: pftree
Version: 3.4.2
Summary: Utility to create dict representations of file system trees.
Home-page: https://github.com/FNNDSC/pftree
Author: FNNDSC
Author-email: dev@babymri.org
License: MIT
License-File: LICENSE
